{"cameraMode":{"drawMode":0,"name":"Shaded","section":"Shading Mode"},"sceneLighting":true,"audioPlay":false,"sceneViewState":{"m_AlwaysRefresh":false,"showFog":true,"showSkybox":true,"showFlares":true,"showImageEffects":true,"showParticleSystems":true,"showVisualEffectGraphs":true,"m_FxEnabled":true},"in2DMode":false,"pivot":{"x":-8.498210906982422,"y":-1.5915770530700684,"z":21.046838760375978},"rotation":{"x":0.1529412865638733,"y":-0.5452433228492737,"z":0.10304231941699982,"w":0.8181740641593933},"size":11.622495651245118,"orthographic":false}